outlet
outlet/builtin_plugins
