Metadata-Version: 1.0
Name: outlet
Version: 0.4.post6
Summary: discord bot framework
Home-page: http://github.com/reshanie/outlet
Author: J Patrick Dill
Author-email: jamespatrickdill@gmail.com
License: MIT
Platform: UNKNOWN
